README.md
setup.py
Outlog.egg-info/PKG-INFO
Outlog.egg-info/SOURCES.txt
Outlog.egg-info/dependency_links.txt
Outlog.egg-info/top_level.txt
outlog/__init__.py
outlog/error.py
outlog/logging.py
outlog/message.py
outlog/util.py