Metadata-Version: 2.1
Name: Outlog
Version: 1.0.4
Summary: Easy way to log data!.
Home-page: https://github.com/zsendokame/outlog
Author: Sendokame
License: UNKNOWN
Platform: UNKNOWN
